pubg_python/__init__.py
pubg_python/base.py
pubg_python/clients.py
pubg_python/decorators.py
pubg_python/exceptions.py
pubg_python/mixins.py
pubg_python/querysets.py
pubg_python/domain/__init__.py
pubg_python/domain/base.py
pubg_python/domain/telemetry/__init__.py
pubg_python/domain/telemetry/base.py
pubg_python/domain/telemetry/data.py
pubg_python/domain/telemetry/events.py
pubg_python/domain/telemetry/objects.py
pubg_python/domain/telemetry/resources.py
pubg_python-0.12.5.dist-info/AUTHORS
pubg_python-0.12.5.dist-info/LICENSE
pubg_python-0.12.5.dist-info/METADATA
pubg_python-0.12.5.dist-info/WHEEL
pubg_python-0.12.5.dist-info/top_level.txt
pubg_python-0.12.5.dist-info/RECORD
