Metadata-Version: 2.1
Name: pubg-python
Version: 0.12.5
Summary: A python wrapper for the PUBG developer API
Home-page: https://github.com/ramonsaraiva/pubg-python
Author: Ramon Saraiva
Author-email: ramonsaraiva@gmail.com
License: MIT
Classifier: Development Status :: 4 - Beta
Classifier: License :: OSI Approved :: MIT License
Classifier: Natural Language :: English
Classifier: Operating System :: OS Independent
Classifier: Programming Language :: Python :: 3
Classifier: Programming Language :: Python :: 3.10
Classifier: Programming Language :: Python :: 3.9
Classifier: Programming Language :: Python :: 3.8
Classifier: Programming Language :: Python :: 3.7
Classifier: Programming Language :: Python :: 3.6
Classifier: Programming Language :: Python :: 3.5
Classifier: Topic :: Utilities
License-File: LICENSE
License-File: AUTHORS
Requires-Dist: requests (>=2.18.4)
Requires-Dist: furl (>=1.0.1)
Requires-Dist: enum34 (>=1.1.6) ; python_version<='3.4'
